LICENSE
MANIFEST.in
README.md
pyproject.toml
requirements.txt
setup.py
dosview/__init__.py
dosview/airdos04.py
dosview/airdos04_info.py
dosview/calibration_widget.py
dosview/eeprom_schema.py
dosview/eeprom_widget.py
dosview/loading_dialog.py
dosview/parsers.py
dosview/rtc_widget.py
dosview/version.py
dosview.egg-info/PKG-INFO
dosview.egg-info/SOURCES.txt
dosview.egg-info/dependency_links.txt
dosview.egg-info/entry_points.txt
dosview.egg-info/requires.txt
dosview.egg-info/top_level.txt
tests/test_parser.py