Metadata-Version: 2.4
Name: dosview
Version: 0.1.23
Summary: A .dos file viewer
Author-email: Roman Dvorak <dvorakroman@ust.cz>
Maintainer-email: Roman Dvorak <dvorakroman@ust.cz>
License:                     GNU GENERAL PUBLIC LICENSE
Project-URL: homepage, https://docs.dos.ust.cz/dosview/
Project-URL: repository, https://github.com/UniversalScientificTechnologies/dosview/
Project-URL: github, https://github.com/UniversalScientificTechnologies/dosview/
Project-URL: issues, https://github.com/UniversalScientificTechnologies/dosview/issues
Project-URL: doccumentation, https://docs.dos.ust.cz/dosview/
Classifier: Development Status :: 3 - Alpha
Classifier: Intended Audience :: Developers
Classifier: License :: OSI Approved :: MIT License
Classifier: Programming Language :: Python :: 3.6
Classifier: Programming Language :: Python :: 3.7
Classifier: Programming Language :: Python :: 3.8
Classifier: Programming Language :: Python :: 3.9
Classifier: Programming Language :: Python :: 3.10
Classifier: Programming Language :: Python :: 3.11
Classifier: Programming Language :: Python :: 3.12
Requires-Python: >=3.6
License-File: LICENSE
Requires-Dist: setuptools
Requires-Dist: matplotlib
Requires-Dist: numpy
Requires-Dist: pandas
Requires-Dist: pyqt5
Requires-Dist: pyqtgraph
Requires-Dist: ft260
Dynamic: license-file
